DISCLAIMER.txt
LICENSE
MANIFEST.in
NOTICE
README.md
requirements-dev.txt
requirements.txt
setup.py
apache_gravitino.egg-info/PKG-INFO
apache_gravitino.egg-info/SOURCES.txt
apache_gravitino.egg-info/dependency_links.txt
apache_gravitino.egg-info/requires.txt
apache_gravitino.egg-info/top_level.txt
gravitino/__init__.py
gravitino/name_identifier.py
gravitino/namespace.py
gravitino/typing.py
gravitino/version.ini
gravitino/api/__init__.py
gravitino/api/audit.py
gravitino/api/auditable.py
gravitino/api/catalog.py
gravitino/api/catalog_change.py
gravitino/api/column.py
gravitino/api/metadata_object.py
gravitino/api/metalake.py
gravitino/api/metalake_change.py
gravitino/api/model_change.py
gravitino/api/model_version_change.py
gravitino/api/schema.py
gravitino/api/schema_change.py
gravitino/api/supports_schemas.py
gravitino/api/credential/__init__.py
gravitino/api/credential/adls_token_credential.py
gravitino/api/credential/azure_account_key_credential.py
gravitino/api/credential/credential.py
gravitino/api/credential/gcs_token_credential.py
gravitino/api/credential/oss_secret_key_credential.py
gravitino/api/credential/oss_token_credential.py
gravitino/api/credential/s3_secret_key_credential.py
gravitino/api/credential/s3_token_credential.py
gravitino/api/credential/supports_credentials.py
gravitino/api/expressions/__init__.py
gravitino/api/expressions/expression.py
gravitino/api/expressions/function_expression.py
gravitino/api/expressions/named_reference.py
gravitino/api/expressions/unparsed_expression.py
gravitino/api/expressions/literals/__init__.py
gravitino/api/expressions/literals/literal.py
gravitino/api/expressions/literals/literals.py
gravitino/api/expressions/sorts/__init__.py
gravitino/api/expressions/sorts/null_ordering.py
gravitino/api/expressions/sorts/sort_direction.py
gravitino/api/expressions/sorts/sort_order.py
gravitino/api/expressions/sorts/sort_orders.py
gravitino/api/file/__init__.py
gravitino/api/file/fileset.py
gravitino/api/file/fileset_change.py
gravitino/api/model/__init__.py
gravitino/api/model/model.py
gravitino/api/model/model_version.py
gravitino/api/tag/__init__.py
gravitino/api/tag/supports_tags.py
gravitino/api/tag/tag.py
