Metadata-Version: 2.1
Name: apache-gravitino
Version: 0.9.0
Summary: Python lib/client for Apache Gravitino
Home-page: https://github.com/apache/gravitino
Author: Apache Software Foundation
Author-email: dev@gravitino.apache.org
Maintainer: Apache Gravitino Community
Maintainer-email: dev@gravitino.apache.org
License: Apache-2.0
Project-URL: Homepage, https://gravitino.apache.org/
Project-URL: Source Code, https://github.com/apache/gravitino
Project-URL: Documentation, https://gravitino.apache.org/docs/overview
Project-URL: Bug Tracker, https://github.com/apache/gravitino/issues
Project-URL: Slack Chat, https://the-asf.slack.com/archives/C078RESTT19
Keywords: Data,AI,metadata,catalog
Classifier: License :: OSI Approved :: Apache Software License
Classifier: Operating System :: OS Independent
Classifier: Programming Language :: Python :: 3.8
Classifier: Programming Language :: Python :: 3.9
Classifier: Programming Language :: Python :: 3.10
Classifier: Programming Language :: Python :: 3.11
Classifier: Programming Language :: Python :: 3.12
Requires-Python: >=3.8
License-File: LICENSE
License-File: NOTICE
Requires-Dist: requests==2.32.3
Requires-Dist: dataclasses-json==0.6.7
Requires-Dist: readerwriterlock==1.0.9
Requires-Dist: fsspec==2024.3.1
Requires-Dist: pyarrow==15.0.2
Requires-Dist: cachetools==5.5.2
Requires-Dist: gcsfs==2024.3.1
Requires-Dist: s3fs==2024.3.1
Requires-Dist: ossfs==2023.12.0
Requires-Dist: adlfs==2023.12.0
Provides-Extra: dev
Requires-Dist: requests==2.32.3; extra == "dev"
Requires-Dist: dataclasses-json==0.6.7; extra == "dev"
Requires-Dist: pylint==3.2.2; extra == "dev"
Requires-Dist: black==24.4.2; extra == "dev"
Requires-Dist: twine==5.1.1; extra == "dev"
Requires-Dist: coverage==7.5.1; extra == "dev"
Requires-Dist: pandas==2.0.3; python_version == "3.8" and extra == "dev"
Requires-Dist: pandas==2.2.3; python_version > "3.8" and extra == "dev"
Requires-Dist: pyarrow==15.0.2; extra == "dev"
Requires-Dist: llama-index==0.11.18; extra == "dev"
Requires-Dist: tenacity==8.3.0; extra == "dev"
Requires-Dist: cachetools==5.5.2; extra == "dev"
Requires-Dist: readerwriterlock==1.0.9; extra == "dev"
Requires-Dist: docker==7.1.0; extra == "dev"
Requires-Dist: pyjwt[crypto]==2.8.0; extra == "dev"
Requires-Dist: jwcrypto==1.5.6; extra == "dev"
Requires-Dist: sphinx==7.1.2; extra == "dev"
Requires-Dist: furo==2024.8.6; extra == "dev"
